claude_profile_switcher/__init__.py
claude_profile_switcher/claude_config.py
claude_profile_switcher/main.py
claude_profile_switcher/models.py
claude_profile_switcher/predefined_profiles.json
claude_profile_switcher/profile_manager.py
claude_profile_switcher/ui.py
claude_profile_switcher-0.1.0.dist-info/METADATA
claude_profile_switcher-0.1.0.dist-info/WHEEL
claude_profile_switcher-0.1.0.dist-info/entry_points.txt
claude_profile_switcher-0.1.0.dist-info/licenses/LICENSE
claude_profile_switcher-0.1.0.dist-info/RECORD
