Metadata-Version: 2.4
Name: claude-profile-switcher
Version: 0.1.0
Summary: A TUI-based Claude Code configuration profile switcher
Project-URL: Homepage, https://github.com/junity/claude-profile-switcher
Project-URL: Repository, https://github.com/junity/claude-profile-switcher
Project-URL: Issues, https://github.com/junity/claude-profile-switcher/issues
Author: Junity
License: MIT
License-File: LICENSE
Keywords: claude,claude-code,cli,profile,switcher,tui
Classifier: Development Status :: 4 - Beta
Classifier: Environment :: Console
Classifier: Intended Audience :: Developers
Classifier: License :: OSI Approved :: MIT License
Classifier: Operating System :: OS Independent
Classifier: Programming Language :: Python :: 3
Classifier: Programming Language :: Python :: 3.9
Classifier: Programming Language :: Python :: 3.10
Classifier: Programming Language :: Python :: 3.11
Classifier: Programming Language :: Python :: 3.12
Classifier: Programming Language :: Python :: 3.13
Classifier: Topic :: Software Development
Classifier: Topic :: Utilities
Requires-Python: >=3.9
